{
  "variants": {
    "facing=east,fill_state=0": {
      "model": "leet_tech:block/energy_cell_front_0",
      "y": 90
    },
    "facing=east,fill_state=1": {
      "model": "leet_tech:block/energy_cell_front_1",
      "y": 90
    },
    "facing=east,fill_state=10": {
      "model": "leet_tech:block/energy_cell_front_10",
      "y": 90
    },
    "facing=east,fill_state=11": {
      "model": "leet_tech:block/energy_cell_front_11",
      "y": 90
    },
    "facing=east,fill_state=12": {
      "model": "leet_tech:block/energy_cell_front_12",
      "y": 90
    },
    "facing=east,fill_state=2": {
      "model": "leet_tech:block/energy_cell_front_2",
      "y": 90
    },
    "facing=east,fill_state=3": {
      "model": "leet_tech:block/energy_cell_front_3",
      "y": 90
    },
    "facing=east,fill_state=4": {
      "model": "leet_tech:block/energy_cell_front_4",
      "y": 90
    },
    "facing=east,fill_state=5": {
      "model": "leet_tech:block/energy_cell_front_5",
      "y": 90
    },
    "facing=east,fill_state=6": {
      "model": "leet_tech:block/energy_cell_front_6",
      "y": 90
    },
    "facing=east,fill_state=7": {
      "model": "leet_tech:block/energy_cell_front_7",
      "y": 90
    },
    "facing=east,fill_state=8": {
      "model": "leet_tech:block/energy_cell_front_8",
      "y": 90
    },
    "facing=east,fill_state=9": {
      "model": "leet_tech:block/energy_cell_front_9",
      "y": 90
    },
    "facing=north,fill_state=0": {
      "model": "leet_tech:block/energy_cell_front_0"
    },
    "facing=north,fill_state=1": {
      "model": "leet_tech:block/energy_cell_front_1"
    },
    "facing=north,fill_state=10": {
      "model": "leet_tech:block/energy_cell_front_10"
    },
    "facing=north,fill_state=11": {
      "model": "leet_tech:block/energy_cell_front_11"
    },
    "facing=north,fill_state=12": {
      "model": "leet_tech:block/energy_cell_front_12"
    },
    "facing=north,fill_state=2": {
      "model": "leet_tech:block/energy_cell_front_2"
    },
    "facing=north,fill_state=3": {
      "model": "leet_tech:block/energy_cell_front_3"
    },
    "facing=north,fill_state=4": {
      "model": "leet_tech:block/energy_cell_front_4"
    },
    "facing=north,fill_state=5": {
      "model": "leet_tech:block/energy_cell_front_5"
    },
    "facing=north,fill_state=6": {
      "model": "leet_tech:block/energy_cell_front_6"
    },
    "facing=north,fill_state=7": {
      "model": "leet_tech:block/energy_cell_front_7"
    },
    "facing=north,fill_state=8": {
      "model": "leet_tech:block/energy_cell_front_8"
    },
    "facing=north,fill_state=9": {
      "model": "leet_tech:block/energy_cell_front_9"
    },
    "facing=south,fill_state=0": {
      "model": "leet_tech:block/energy_cell_front_0",
      "y": 180
    },
    "facing=south,fill_state=1": {
      "model": "leet_tech:block/energy_cell_front_1",
      "y": 180
    },
    "facing=south,fill_state=10": {
      "model": "leet_tech:block/energy_cell_front_10",
      "y": 180
    },
    "facing=south,fill_state=11": {
      "model": "leet_tech:block/energy_cell_front_11",
      "y": 180
    },
    "facing=south,fill_state=12": {
      "model": "leet_tech:block/energy_cell_front_12",
      "y": 180
    },
    "facing=south,fill_state=2": {
      "model": "leet_tech:block/energy_cell_front_2",
      "y": 180
    },
    "facing=south,fill_state=3": {
      "model": "leet_tech:block/energy_cell_front_3",
      "y": 180
    },
    "facing=south,fill_state=4": {
      "model": "leet_tech:block/energy_cell_front_4",
      "y": 180
    },
    "facing=south,fill_state=5": {
      "model": "leet_tech:block/energy_cell_front_5",
      "y": 180
    },
    "facing=south,fill_state=6": {
      "model": "leet_tech:block/energy_cell_front_6",
      "y": 180
    },
    "facing=south,fill_state=7": {
      "model": "leet_tech:block/energy_cell_front_7",
      "y": 180
    },
    "facing=south,fill_state=8": {
      "model": "leet_tech:block/energy_cell_front_8",
      "y": 180
    },
    "facing=south,fill_state=9": {
      "model": "leet_tech:block/energy_cell_front_9",
      "y": 180
    },
    "facing=west,fill_state=0": {
      "model": "leet_tech:block/energy_cell_front_0",
      "y": 270
    },
    "facing=west,fill_state=1": {
      "model": "leet_tech:block/energy_cell_front_1",
      "y": 270
    },
    "facing=west,fill_state=10": {
      "model": "leet_tech:block/energy_cell_front_10",
      "y": 270
    },
    "facing=west,fill_state=11": {
      "model": "leet_tech:block/energy_cell_front_11",
      "y": 270
    },
    "facing=west,fill_state=12": {
      "model": "leet_tech:block/energy_cell_front_12",
      "y": 270
    },
    "facing=west,fill_state=2": {
      "model": "leet_tech:block/energy_cell_front_2",
      "y": 270
    },
    "facing=west,fill_state=3": {
      "model": "leet_tech:block/energy_cell_front_3",
      "y": 270
    },
    "facing=west,fill_state=4": {
      "model": "leet_tech:block/energy_cell_front_4",
      "y": 270
    },
    "facing=west,fill_state=5": {
      "model": "leet_tech:block/energy_cell_front_5",
      "y": 270
    },
    "facing=west,fill_state=6": {
      "model": "leet_tech:block/energy_cell_front_6",
      "y": 270
    },
    "facing=west,fill_state=7": {
      "model": "leet_tech:block/energy_cell_front_7",
      "y": 270
    },
    "facing=west,fill_state=8": {
      "model": "leet_tech:block/energy_cell_front_8",
      "y": 270
    },
    "facing=west,fill_state=9": {
      "model": "leet_tech:block/energy_cell_front_9",
      "y": 270
    }
  }
}